Code/Chapter2/multidrive/multidrive.sv
module multidrive (
    input  a, b,
    output wire out_wire,
    output reg out_reg,
    output logic out_logic
);

assign out_wire = a;
assign out_wire = b;

always @(*) begin
    out_reg = a;
    out_reg = b;
end

assign out_logic = a;
assign out_logic = b;
endmodule

module tb;
    reg a, b;
    wire out_wire;
    reg out_reg;
    logic out_logic;

    multidrive md (
        .a(a),
        .b(b),
        .out_wire(out_wire),
        .out_reg(out_reg),
        .out_logic(out_logic)
    );

initial begin

    $monitor ("Time = %0t | a = %b, b = %b => out_wire = %b | out_reg = %b | out_logic = %b", $time, a, b, out_wire, out_reg, out_logic);

    $dumpfile("dump.vcd");
    $dumpvars(0, tb);
    //0 vs 1
    a = 1'b0; b = 1'b0; #10;
    a = 1'b0; b = 1'b1; #10;
    a = 1'b1; b = 1'b0; #10;
    a = 1'b1; b = 1'b1; #10;
    //0 1 vs x z
    a = 1'b0; b = 1'bx; #10;
    a = 1'b0; b = 1'bz; #10;
    a = 1'b1; b = 1'bx; #10;
    a = 1'b1; b = 1'bz; #10;
    //x z vs 0 1
    a = 1'bx; b = 1'b0; #10;
    a = 1'bx; b = 1'b1; #10;
    a = 1'bz; b = 1'b0; #10;
    a = 1'bz; b = 1'b1; #10;
    // x vs z
    a = 1'bx; b = 1'bx; #10;
    a = 1'bx; b = 1'bz; #10;
    a = 1'bz; b = 1'bx; #10;
    a = 1'bz; b = 1'bz; #10;
    $finish;
end
endmodule

Code/Chapter2/multidrive/dump.vcd
$date
	Wed Apr  2 22:17:08 2025
$end
$version
	QuestaSim Version 2024.1
$end
$timescale
	1ns
$end

$scope module tb $end
$var reg 1 ! a $end
$var reg 1 " b $end
$var wire 1 # out_wire $end
$var reg 1 $ out_reg $end
$var reg 1 % out_logic $end

$scope module md $end
$var wire 1 & a $end
$var wire 1 ' b $end
$var wire 1 # out_wire $end
$var reg 1 ( out_reg $end
$var reg 1 ) out_logic $end
$upscope $end
$upscope $end
$enddefinitions $end
#0
$dumpvars
0!
0"
0$
0%
0(
0)
0#
0'
0&
$end
#10
1"
1'
x#
1(
1)
1%
1$
#20
1!
0"
1&
0'
0(
0)
0%
0$
#30
1"
1'
1#
1(
1)
1%
1$
#40
0!
x"
0&
x'
x#
0(
x(
0)
x)
x%
x$
#50
z"
z'
0#
0(
z(
0)
z)
z%
z$
#60
1!
x"
1&
x'
x#
1(
x(
1)
x)
x%
x$
#70
z"
z'
1#
1(
z(
1)
z)
z%
z$
#80
x!
0"
x&
0'
x#
x(
0(
x)
0)
0%
0$
#90
1"
1'
x(
1(
x)
1)
1%
1$
#100
z!
0"
z&
0'
0#
z(
0(
z)
0)
0%
0$
#110
1"
1'
1#
z(
1(
z)
1)
1%
1$
#120
x!
x"
x&
x'
x#
x(
x)
x%
x$
#130
z"
z'
z(
z)
z%
z$
#140
z!
x"
z&
x'
x(
x)
x%
x$
#150
z"
z'
z#
z(
z)
z%
z$
